stenographer/__init__.py
stenographer/codes.py
stenographer/transcriber.py
stenographer/translator.py
stenographer/utils.py
whisper_stenographer-0.0.0.dist-info/LICENSE
whisper_stenographer-0.0.0.dist-info/METADATA
whisper_stenographer-0.0.0.dist-info/WHEEL
whisper_stenographer-0.0.0.dist-info/top_level.txt
whisper_stenographer-0.0.0.dist-info/RECORD
